repro_eval/Evaluator.py
repro_eval/__init__.py
repro_eval/__main__.py
repro_eval/config.py
repro_eval/metadata.py
repro_eval/util.py
repro_eval/measure/__init__.py
repro_eval/measure/document_order.py
repro_eval/measure/effectiveness.py
repro_eval/measure/overall_effects.py
repro_eval/measure/statistics.py
repro_eval/measure/external/__init__.py
repro_eval/measure/external/rbo.py
repro_eval/resources/extensions.json
repro_eval-0.4.0.dist-info/LICENSE
repro_eval-0.4.0.dist-info/METADATA
repro_eval-0.4.0.dist-info/WHEEL
repro_eval-0.4.0.dist-info/top_level.txt
repro_eval-0.4.0.dist-info/RECORD
