Metadata-Version: 2.1
Name: repro-eval
Version: 0.4.0
Summary: A tool to quantify the replicability and reproducibility of system-oriented IR experiments.
Home-page: http://github.com/irgroup/repro_eval
Author: Timo Breuer
Author-email: timo.breuer@th-koeln.de
License: MIT
Platform: UNKNOWN
Requires-Dist: pytrec-eval
Requires-Dist: numpy
Requires-Dist: scipy
Requires-Dist: tqdm
Requires-Dist: ruamel.yaml
Requires-Dist: GitPython
Requires-Dist: py-cpuinfo
